{"stats":{"minecraft:custom":{"minecraft:jump":9,"minecraft:leave_game":1,"minecraft:time_since_rest":21389,"minecraft:crouch_one_cm":184,"minecraft:play_one_minute":21389,"minecraft:sprint_one_cm":1363,"minecraft:time_since_death":21389,"minecraft:walk_one_cm":4954,"minecraft:sneak_time":168,"minecraft:mob_kills":38,"minecraft:fly_one_cm":115363},"minecraft:killed":{"minecraft:slime":36},"minecraft:used":{"mts:iv_tcp_v3_utility.trin_juggernaut_mod_truck_tq3_shagbark_g":1,"mts:iv_tcp_v3_utility.trin_tormador_tq3_customlivery2_w":1,"mts:iv_tcp_v3_txs.trin_formula_tungsten":2,"mts:iv_tcp_v3_service.trin_ropy_4door_police_generic_g":1,"mts:iv_tcp_v3_utility.trin_foragon_nrml_pickup_tq1_purewhite_g":1,"mts:iv_tcp_v3_txs.trin_gobig_txs_pickup_6x6_pureblack_w":1,"mts:ivairlinerpack.dc-8-30":1,"mts:auweschvebm.auweschveb_vehicle_a_yf22_shsr":1},"minecraft:picked_up":{"minecraft:slime_ball":14,"mts:iv_tcp_v3_service.trin_ropy_4door_police_generic_g":1,"mts:iv_tcp_v3_txs.trin_gobig_txs_pickup_6x6_pureblack_w":1}},"DataVersion":2586}